{"trial_id": "039", "hyperparameters": {"space": [{"class_name": "Int", "config": {"name": "num_layers", "default": null, "conditions": [], "min_value": 1, "max_value": 10, "step": 1, "sampling": "linear"}}, {"class_name": "Int", "config": {"name": "units_0", "default": null, "conditions": [], "min_value": 1, "max_value": 50, "step": 1, "sampling": "linear"}}, {"class_name": "Choice", "config": {"name": "learning_rate", "default": 0.01, "conditions": [], "values": [0.01, 0.001, 0.0001, 1e-05], "ordered": true}}, {"class_name": "Int", "config": {"name": "units_1", "default": null, "conditions": [], "min_value": 1, "max_value": 50, "step": 1, "sampling": "linear"}}, {"class_name": "Int", "config": {"name": "units_2", "default": null, "conditions": [], "min_value": 1, "max_value": 50, "step": 1, "sampling": "linear"}}, {"class_name": "Int", "config": {"name": "units_3", "default": null, "conditions": [], "min_value": 1, "max_value": 50, "step": 1, "sampling": "linear"}}, {"class_name": "Int", "config": {"name": "units_4", "default": null, "conditions": [], "min_value": 1, "max_value": 50, "step": 1, "sampling": "linear"}}, {"class_name": "Int", "config": {"name": "units_5", "default": null, "conditions": [], "min_value": 1, "max_value": 50, "step": 1, "sampling": "linear"}}, {"class_name": "Int", "config": {"name": "units_6", "default": null, "conditions": [], "min_value": 1, "max_value": 50, "step": 1, "sampling": "linear"}}, {"class_name": "Int", "config": {"name": "units_7", "default": null, "conditions": [], "min_value": 1, "max_value": 50, "step": 1, "sampling": "linear"}}, {"class_name": "Int", "config": {"name": "units_8", "default": null, "conditions": [], "min_value": 1, "max_value": 50, "step": 1, "sampling": "linear"}}, {"class_name": "Int", "config": {"name": "units_9", "default": null, "conditions": [], "min_value": 1, "max_value": 50, "step": 1, "sampling": "linear"}}], "values": {"num_layers": 7, "units_0": 4, "learning_rate": 0.01, "units_1": 38, "units_2": 32, "units_3": 48, "units_4": 41, "units_5": 15, "units_6": 18, "units_7": 41, "units_8": 22, "units_9": 46}}, "metrics": {"metrics": {"loss": {"direction": "min", "observations": [{"value": [4445.4912109375], "step": 95}]}, "mean_squared_error": {"direction": "min", "observations": [{"value": [4445.4912109375], "step": 95}]}, "rmse": {"direction": "min", "observations": [{"value": [51.109195709228516], "step": 95}]}, "r_square": {"direction": "min", "observations": [{"value": [0.169194757938385], "step": 95}]}, "val_loss": {"direction": "min", "observations": [{"value": [3478.861328125], "step": 95}]}, "val_mean_squared_error": {"direction": "min", "observations": [{"value": [3478.861328125], "step": 95}]}, "val_rmse": {"direction": "min", "observations": [{"value": [44.23384475708008], "step": 95}]}, "val_r_square": {"direction": "min", "observations": [{"value": [0.24697302281856537], "step": 95}]}}}, "score": 3478.861328125, "best_step": 95, "status": "COMPLETED", "message": null}